{
  "empresa_id": 3,
  "modulo": "faturamento",
  "usuario": "THIAGO_SAFIA",
  "registrado_em_iso": "2026-03-29T14:50:45+00:00",
  "quantidade_arquivos": 39,
  "arquivos": [
    "SAFIA FILIAL 05.03.2026.xlsx",
    "SAFIA FILIAL 06.03.2026.xlsx",
    "SAFIA FILIAL 07.03.2026.xlsx",
    "SAFIA FILIAL 09.03.2026.xlsx",
    "SAFIA FILIAL 10.03.2026.xlsx",
    "SAFIA FILIAL 11.03.26.xlsx",
    "SAFIA FILIAL 12.03.2026.xlsx",
    "SAFIA FILIAL 13.03.2026.xlsx",
    "SAFIA FILIAL 14.03.2026.xlsx",
    "SAFIA FILIAL 16.03.2026.xlsx",
    "SAFIA FILIAL 17.03.2026.xlsx",
    "SAFIA FILIAL 18.03.2026.xlsx",
    "SAFIA FILIAL 19.03.2026.xlsx",
    "SAFIA FILIAL 20.03.2026.xlsx",
    "SAFIA FILIAL 21.03.2026.xlsx",
    "SAFIA FILIAL 23.03.2026.xlsx",
    "SAFIA FILIAL 24.03.2026.xlsx",
    "SAFIA FILIAL 25.03.2026.xlsx",
    "SAFIA FILIAL 26.03.2026.xlsx",
    "SAFIA MATRIZ 05.03.2026.xlsx",
    "SAFIA MATRIZ 06.03.2026.xlsx",
    "SAFIA MATRIZ 07.03.2026.xlsx",
    "SAFIA MATRIZ 09.03.2026.xlsx",
    "SAFIA MATRIZ 10.03.2026.xlsx",
    "SAFIA MATRIZ 11.03.26.xlsx",
    "SAFIA MATRIZ 12.03.2026.xlsx",
    "SAFIA MATRIZ 13.03.2026.xlsx",
    "SAFIA MATRIZ 14.03.2026.xlsx",
    "SAFIA MATRIZ 16.03.2026.xlsx",
    "SAFIA MATRIZ 17.03.2026.xlsx",
    "SAFIA MATRIZ 18.03.2026.xlsx",
    "SAFIA MATRIZ 19.03.2026.xlsx",
    "SAFIA MATRIZ 20.03.2026.xlsx",
    "SAFIA MATRIZ 21.03.2026.xlsx",
    "SAFIA MATRIZ 23.03.2026.xlsx",
    "SAFIA MATRIZ 24.03.2026.xlsx",
    "SAFIA MATRIZ 25.03.2026.xlsx",
    "SAFIA MATRIZ 26.03.2026.xlsx",
    "01.03.2026 A 26.03.2026.xlsx"
  ],
  "faturamento_vendedores_total_legacy": 76
}